<?xml version="1.0" encoding="iso-8859-1"?>

<root>
	<!-- Assets and Windows  -->
	<includefile source="xml/rr_images.xml" />
	<includefile source="xml/rr_strings.xml" />
	<includefile source="xml/rr_frames.xml"/>
	<includefile source="roll/rr_manualroll_entry.xml" />
	<includefile source="roll/rr_stagedroll_entry.xml"/>

	<!-- Manager Code -->
	<script name="RR" file="scripts/rr.lua"/>
	<script name="RRActionManager" file="scripts/rr_manager_action.lua"/>
	<script name="RRTowerManager" file="scripts/rr_manager_tower.lua"/>
	<script name="RRRollManager" file="scripts/rr_manager_roll.lua"/>
	<script name="RRDropManager" file="scripts/rr_manager_drop.lua"/>
	<script name="RRManagerStaged" file="scripts/rr_manager_staged.lua"/>

	<!-- Ruleset Specific Code Changes -->
	<script name="RRCoreRPG" file="scripts/rr_config_CoreRPG.lua" ruleset="CoreRPG"/>
	<script name="RR4E" file="scripts/rr_config_4E.lua" ruleset="4E"/>
	<script name="RR2E" file="scripts/rr_config_2E.lua" ruleset="2E"/>
	<script name="RRPFRPG2" file="scripts/rr_config_PFRPG2.lua" ruleset="PFRPG2"/>

	<!-- Console Windows -->
	<includefile source="console/rr_template_rollModule.xml"/>
	<includefile source="console/rr_console.xml"/>
	<includefile source="console/rr_console_buttons.xml"/>
	<includefile source="console/rr_templates.xml"/>
	<includefile source="console/rr_console_options.xml"/>
	<includefile source="console/rr_console_staged.xml"/>

	<!-- Ruleset Specific UI Changes -->
	<includefile source="console/rr_config_4E.xml" ruleset="4E"/>
	<includefile source="console/rr_config_2E.xml" ruleset="2E"/>
	<includefile source="console/rr_config_CoreRPG.xml" ruleset="CoreRPG"/>

	<!-- Miscellaneous Changes -->
	<includefile source="desktop/rr_desktop_panels.xml"/>
</root>
